{
    "uuid": "08727238-eb79-45c3-87ee-fbf79da6a610",
    "f_table_schema": "fkg",
    "f_table_name": "t_5602_p_zoner",
    "f_geometry_column": "geometri",
    "f_table_abstract": null,
    "f_table_title": "P-zoner (5602) ",
    "pkey": "objekt_id",
    "rel_type": "VIEW",
    "coord_dimension": 2,
    "type": "MULTIPOLYGON",
    "srid": 25832,
    "authentication": "Write",
    "layergroup": "Vej og Trafik",
    "sort_id": 130,
    "tags": [
        "udgivet"
    ],
    "fields": {
        "temakode": {
            "type": "integer",
            "comment": "Feltet benyttes til at identificere datas\u00e6ttet via en kode. Temakoden er unik, og kan bruges bl.a. som identifikator i metadatabasen.",
            "num": 1,
            "full_type": "integer",
            "typname": "int4",
            "is_array": false,
            "character_maximum_length": null,
            "numeric_precision": 32,
            "numeric_scale": 0,
            "max_bytes": 4,
            "reference": null,
            "restriction": null,
            "alias": "",
            "queryable": false,
            "sort_id": 10
        },
        "temanavn": {
            "type": "text",
            "comment": "Feltet benyttes til at overs\u00e6tte\/vise koden til tekst.",
            "num": 2,
            "full_type": "text",
            "typname": "text",
            "is_array": false,
            "character_maximum_length": null,
            "numeric_precision": null,
            "numeric_scale": null,
            "max_bytes": 1073741824,
            "reference": null,
            "restriction": null,
            "alias": "",
            "queryable": false,
            "sort_id": 20
        },
        "objekt_id": {
            "type": "uuid",
            "comment": "Entydigt ID for et objekt i et tema. Hvis objekter er opdaterede, har de historiske objekter samme Objekt_id som det g\u00e6ldende, men forskellige Versions_id\u2019er. Objekt_id\u2019en anvendes som generel reference til et objekt i et tema.",
            "num": 3,
            "full_type": "uuid",
            "typname": "uuid",
            "is_array": false,
            "character_maximum_length": null,
            "numeric_precision": null,
            "numeric_scale": null,
            "max_bytes": 16,
            "reference": null,
            "restriction": null,
            "alias": "",
            "queryable": false,
            "sort_id": 30
        },
        "versions_id": {
            "type": "uuid",
            "comment": "Instansobjekt ID. Unikt objekt ID p\u00e5 tv\u00e6rs af datas\u00e6t og over tid. Mens et objekt bevarer samme Objekt_id fra f\u00f8dsel til d\u00f8d, vil Versions_id \u00e6ndres ved enhver opdatering af objektet.",
            "num": 4,
            "full_type": "uuid",
            "typname": "uuid",
            "is_array": false,
            "character_maximum_length": null,
            "numeric_precision": null,
            "numeric_scale": null,
            "max_bytes": 16,
            "reference": null,
            "restriction": null,
            "alias": "",
            "queryable": true,
            "sort_id": 40
        },
        "systid_fra": {
            "type": "timestamp with time zone",
            "comment": "Dato og tidspunkt for start af objektets systemm\u00e6ssige gyldighed. S\u00e6ttes af systemet ved oprettelse af nye objekter eller ved\u00e6ndringer, hvor der samtidig oprettes et historisk objekt. Dato og tidspunkt genereres af systemet ved indl\u00e6gning i databasen. Feltet beskriver systemgyldighed, og m\u00e5 ikke forveksles med forvaltningsm\u00e6ssig gyldighed.",
            "num": 5,
            "full_type": "timestamp with time zone",
            "typname": "timestamptz",
            "is_array": false,
            "character_maximum_length": null,
            "numeric_precision": null,
            "numeric_scale": null,
            "max_bytes": 8,
            "reference": null,
            "restriction": null,
            "alias": "",
            "queryable": false,
            "sort_id": 50
        },
        "systid_til": {
            "type": "timestamp with time zone",
            "comment": "Dato og tidspunkt for slut af objektets systemm\u00e6ssige gyldighed. S\u00e6ttes af systemet ved sletning af objekter, eller ved \u00e6ndringer, hvor der oprettes et historisk objekt. Dato og tidspunkt generes af systemet ved sletning eller \u00e6ndring i databasen.  Et g\u00e6ldende objekt har altid Systid_til = NULL. Feltet beskriver systemgyldighed og m\u00e5 ikke forveksles med forvaltningsm\u00e6ssig gyldighed.",
            "num": 6,
            "full_type": "timestamp with time zone",
            "typname": "timestamptz",
            "is_array": false,
            "character_maximum_length": null,
            "numeric_precision": null,
            "numeric_scale": null,
            "max_bytes": 8,
            "reference": null,
            "restriction": null,
            "alias": "",
            "queryable": false,
            "sort_id": 60
        },
        "oprettet": {
            "type": "timestamp with time zone",
            "comment": "Dato og tidspunkt for objektets systemm\u00e6ssige oprettelse svarer til f\u00f8rste Systid_fra registreret p\u00e5 et Objekt_id, hvorved oprettelsestidspunktet altid fremg\u00e5r, uanset hvor mange \u00e6ndringer et objekt har gennemg\u00e5et. Dato og tidspunkt genereres af systemet ved indl\u00e6gning i databasen.",
            "num": 7,
            "full_type": "timestamp with time zone",
            "typname": "timestamptz",
            "is_array": false,
            "character_maximum_length": null,
            "numeric_precision": null,
            "numeric_scale": null,
            "max_bytes": 8,
            "reference": null,
            "restriction": null,
            "alias": "",
            "queryable": false,
            "sort_id": 70
        },
        "cvr_kode": {
            "type": "integer",
            "comment": "Feltet benyttes til at angive CVR-koden for objektets ansvarlige myndighed. Systemet b\u00f8r kunne se hvilken kommune brugeren kommer fra via login\u2019et og selv udfylde feltet.",
            "num": 8,
            "full_type": "integer",
            "typname": "int4",
            "is_array": false,
            "character_maximum_length": null,
            "numeric_precision": 32,
            "numeric_scale": 0,
            "max_bytes": 4,
            "reference": [
                "fkg.d_basis_ansvarlig_myndighed.cvr_kode"
            ],
            "restriction": [
                {
                    "value": 10000001,
                    "alias": "supercykelstisekretariatet"
                },
                {
                    "value": 10000002,
                    "alias": "Tommeruppernes Lokalr\u00e5d"
                },
                {
                    "value": 10000003,
                    "alias": "geoinfovejle"
                },
                {
                    "value": 10000004,
                    "alias": "sporapp"
                },
                {
                    "value": 10000005,
                    "alias": "undervisning"
                },
                {
                    "value": 10000006,
                    "alias": "GeoInfoSonderborg"
                },
                {
                    "value": 10000007,
                    "alias": "Kyst Til Kyst"
                },
                {
                    "value": 10000008,
                    "alias": "Naturpark Lilleb\u00e6lt"
                },
                {
                    "value": 10000009,
                    "alias": "itu_anastassia"
                },
                {
                    "value": 10000010,
                    "alias": "CT_marcoberends"
                },
                {
                    "value": 10000011,
                    "alias": "Havmilj\u00f8vogterne"
                },
                {
                    "value": 10000012,
                    "alias": "Konge\u00e5sti"
                },
                {
                    "value": 10294819,
                    "alias": "Konkurrence- og Forbrugerstyrelsen"
                },
                {
                    "value": 11259979,
                    "alias": "Frederiksberg Kommune"
                },
                {
                    "value": 11715311,
                    "alias": "Lyngby-Taarb\u00e6k Kommune"
                },
                {
                    "value": 11931316,
                    "alias": "Ish\u00f8j Kommune"
                },
                {
                    "value": 12881517,
                    "alias": "Drag\u00f8r Kommune"
                },
                {
                    "value": 15524286,
                    "alias": "geoinfo"
                },
                {
                    "value": 16287180,
                    "alias": "Forsvarsministeriets Ejendomsstyrelse"
                },
                {
                    "value": 17156616,
                    "alias": "Dansk e-Mobilitet"
                },
                {
                    "value": 18282690,
                    "alias": "Destination Fyn"
                },
                {
                    "value": 18957981,
                    "alias": "Ringsted Kommune"
                },
                {
                    "value": 19438414,
                    "alias": "Gentofte Kommune"
                },
                {
                    "value": 19501817,
                    "alias": "H\u00f8je-Taastrup Kommune"
                },
                {
                    "value": 19583910,
                    "alias": "Vallensb\u00e6k Kommune"
                },
                {
                    "value": 20014784,
                    "alias": "Geopartner Landinspekt\u00f8rer A\/S"
                },
                {
                    "value": 20310413,
                    "alias": "T\u00e5rnby Kommune"
                },
                {
                    "value": 23717382,
                    "alias": "H\u00e6rvejen"
                },
                {
                    "value": 23795515,
                    "alias": "Sams\u00f8 Kommune"
                },
                {
                    "value": 25118359,
                    "alias": "Norlys"
                },
                {
                    "value": 25775635,
                    "alias": "Christians\u00f8"
                },
                {
                    "value": 25798376,
                    "alias": "Milj\u00f8styrelsen"
                },
                {
                    "value": 26696348,
                    "alias": "Bornholms Regionskommune"
                },
                {
                    "value": 27782515,
                    "alias": "Idr\u00e6ttens Analyseinstitut"
                },
                {
                    "value": 28297947,
                    "alias": "EWII"
                },
                {
                    "value": 28326858,
                    "alias": "Nordsj\u00e6llands Brandv\u00e6sen"
                },
                {
                    "value": 28856075,
                    "alias": "\u00c6r\u00f8 Kommune"
                },
                {
                    "value": 29188327,
                    "alias": "Fures\u00f8 Kommune"
                },
                {
                    "value": 29188335,
                    "alias": "Fredensborg Kommune"
                },
                {
                    "value": 29188378,
                    "alias": "Rudersdal Kommune"
                },
                {
                    "value": 29188386,
                    "alias": "Egedal Kommune"
                },
                {
                    "value": 29188416,
                    "alias": "Halsn\u00e6s Kommune"
                },
                {
                    "value": 29188440,
                    "alias": "Gribskov Kommune"
                },
                {
                    "value": 29188459,
                    "alias": "Odsherred Kommune"
                },
                {
                    "value": 29188475,
                    "alias": "Faxe Kommune"
                },
                {
                    "value": 29188505,
                    "alias": "Slagelse Kommune"
                },
                {
                    "value": 29188548,
                    "alias": "Lejre Kommune"
                },
                {
                    "value": 29188572,
                    "alias": "Lolland Kommune"
                },
                {
                    "value": 29188599,
                    "alias": "Guldborgsund Kommune"
                },
                {
                    "value": 29188645,
                    "alias": "Faaborg-Midtfyn Kommune"
                },
                {
                    "value": 29188947,
                    "alias": "Nordfyns Kommune"
                },
                {
                    "value": 29188955,
                    "alias": "Langeland Kommune"
                },
                {
                    "value": 29189129,
                    "alias": "Frederikssund Kommune"
                },
                {
                    "value": 29189366,
                    "alias": "Hiller\u00f8d Kommune"
                },
                {
                    "value": 29189374,
                    "alias": "K\u00f8ge Kommune"
                },
                {
                    "value": 29189382,
                    "alias": "Hj\u00f8rring Kommune"
                },
                {
                    "value": 29189404,
                    "alias": "Roskilde Kommune"
                },
                {
                    "value": 29189420,
                    "alias": "Aalborg Kommune"
                },
                {
                    "value": 29189439,
                    "alias": "Jammerbugt Kommune"
                },
                {
                    "value": 29189447,
                    "alias": "Holb\u00e6k Kommune"
                },
                {
                    "value": 29189455,
                    "alias": "Mariagerfjord Kommune"
                },
                {
                    "value": 29189463,
                    "alias": "Rebild Kommune"
                },
                {
                    "value": 29189471,
                    "alias": "Vesthimmerlands Kommune"
                },
                {
                    "value": 29189498,
                    "alias": "Frederikshavn Kommune"
                },
                {
                    "value": 29189501,
                    "alias": "Br\u00f8nderslev Kommune"
                },
                {
                    "value": 29189560,
                    "alias": "Thisted Kommune"
                },
                {
                    "value": 29189579,
                    "alias": "Skive Kommune"
                },
                {
                    "value": 29189587,
                    "alias": "Hedensted Kommune"
                },
                {
                    "value": 29189595,
                    "alias": "Kalundborg Kommune"
                },
                {
                    "value": 29189609,
                    "alias": "Ringk\u00f8bing-Skjern Kommune"
                },
                {
                    "value": 29189617,
                    "alias": "Ikast-Brande Kommune"
                },
                {
                    "value": 29189625,
                    "alias": "N\u00e6stved Kommune"
                },
                {
                    "value": 29189633,
                    "alias": "Skanderborg Kommune"
                },
                {
                    "value": 29189641,
                    "alias": "Silkeborg Kommune"
                },
                {
                    "value": 29189668,
                    "alias": "Randers Kommune"
                },
                {
                    "value": 29189676,
                    "alias": "Vordingborg Kommune"
                },
                {
                    "value": 29189684,
                    "alias": "Middelfart Kommune"
                },
                {
                    "value": 29189692,
                    "alias": "Assens Kommune"
                },
                {
                    "value": 29189706,
                    "alias": "Kerteminde Kommune"
                },
                {
                    "value": 29189714,
                    "alias": "Favrskov Kommune"
                },
                {
                    "value": 29189722,
                    "alias": "Nyborg Kommune"
                },
                {
                    "value": 29189730,
                    "alias": "Svendborg Kommune"
                },
                {
                    "value": 29189757,
                    "alias": "Haderslev Kommune"
                },
                {
                    "value": 29189765,
                    "alias": "Billund Kommune"
                },
                {
                    "value": 29189773,
                    "alias": "S\u00f8nderborg Kommune"
                },
                {
                    "value": 29189781,
                    "alias": "T\u00f8nder Kommune"
                },
                {
                    "value": 29189803,
                    "alias": "Esbjerg Kommune"
                },
                {
                    "value": 29189811,
                    "alias": "Varde Kommune"
                },
                {
                    "value": 29189838,
                    "alias": "Vejen Kommune"
                },
                {
                    "value": 29189846,
                    "alias": "Viborg Kommune"
                },
                {
                    "value": 29189854,
                    "alias": "Aabenraa Kommune"
                },
                {
                    "value": 29189889,
                    "alias": "Horsens Kommune"
                },
                {
                    "value": 29189897,
                    "alias": "Kolding Kommune"
                },
                {
                    "value": 29189900,
                    "alias": "Vejle Kommune"
                },
                {
                    "value": 29189919,
                    "alias": "Herning Kommune"
                },
                {
                    "value": 29189927,
                    "alias": "Holstebro Kommune"
                },
                {
                    "value": 29189935,
                    "alias": "Lemvig Kommune"
                },
                {
                    "value": 29189951,
                    "alias": "Struer Kommune"
                },
                {
                    "value": 29189978,
                    "alias": "Syddjurs Kommune"
                },
                {
                    "value": 29189986,
                    "alias": "Norddjurs Kommune"
                },
                {
                    "value": 29189994,
                    "alias": "Sor\u00f8 Kommune"
                },
                {
                    "value": 29208654,
                    "alias": "Stevns Kommune"
                },
                {
                    "value": 31210917,
                    "alias": "Fan\u00f8 Kommune"
                },
                {
                    "value": 31351901,
                    "alias": "Spor"
                },
                {
                    "value": 32264328,
                    "alias": "Odder Kommune"
                },
                {
                    "value": 32468349,
                    "alias": "CLEVER A\/S"
                },
                {
                    "value": 33157274,
                    "alias": "Naturstyrelsen"
                },
                {
                    "value": 33284114,
                    "alias": "Styrelsen for Dataforsyning og Effektivisering"
                },
                {
                    "value": 34009570,
                    "alias": "Beredskab & Sikkerhed"
                },
                {
                    "value": 34206228,
                    "alias": "Erhvervshus Fyn P\/S"
                },
                {
                    "value": 34897034,
                    "alias": "Destination Sj\u00e6lland A\/S"
                },
                {
                    "value": 35147268,
                    "alias": "Nationalpark Mols Bjerge"
                },
                {
                    "value": 35209115,
                    "alias": "Odense Kommune"
                },
                {
                    "value": 35379193,
                    "alias": "MapCentia"
                },
                {
                    "value": 35432795,
                    "alias": "Sydvestjysk Brandv\u00e6sen"
                },
                {
                    "value": 35434399,
                    "alias": "Midt- og Sydsj\u00e6llands Brand & Redning"
                },
                {
                    "value": 35438718,
                    "alias": "Brand & Redning S\u00f8nderjylland"
                },
                {
                    "value": 35439862,
                    "alias": "Syd\u00f8stjyllands Brandv\u00e6sen"
                },
                {
                    "value": 35440178,
                    "alias": "Hovedstadens Beredskab"
                },
                {
                    "value": 36146702,
                    "alias": "Dansk Cykelturisme"
                },
                {
                    "value": 36471271,
                    "alias": "DKNT"
                },
                {
                    "value": 36920483,
                    "alias": "ParksnTrails"
                },
                {
                    "value": 36986719,
                    "alias": "Geopark Odsherred"
                },
                {
                    "value": 37137502,
                    "alias": "Midtjysk Brand & Redning"
                },
                {
                    "value": 37164712,
                    "alias": "\u00d8stjyllands Brandv\u00e6sen"
                },
                {
                    "value": 37176478,
                    "alias": "SkjoldungernesLand"
                },
                {
                    "value": 37197580,
                    "alias": "Vestsj\u00e6llands Brandv\u00e6sen"
                },
                {
                    "value": 37207969,
                    "alias": "Brand & Redning Midtvest"
                },
                {
                    "value": 37242985,
                    "alias": "TrekantBrand"
                },
                {
                    "value": 37265209,
                    "alias": "Beredskab Fyn"
                },
                {
                    "value": 39170418,
                    "alias": "OK A.M.B.A."
                },
                {
                    "value": 40220321,
                    "alias": "Herslev Bylaug"
                },
                {
                    "value": 40632301,
                    "alias": "Beredskab 4K"
                },
                {
                    "value": 40657339,
                    "alias": "Spirii"
                },
                {
                    "value": 41333014,
                    "alias": "Mors\u00f8 Kommune"
                },
                {
                    "value": 41575727,
                    "alias": "SAMSIK"
                },
                {
                    "value": 41668385,
                    "alias": "Monta ApS"
                },
                {
                    "value": 42309443,
                    "alias": "qLER ApS"
                },
                {
                    "value": 42885746,
                    "alias": "E.ON"
                },
                {
                    "value": 44023911,
                    "alias": "Greve Kommune"
                },
                {
                    "value": 45973328,
                    "alias": "L\u00e6s\u00f8 Kommune"
                },
                {
                    "value": 55133018,
                    "alias": "Aarhus Kommune"
                },
                {
                    "value": 55606617,
                    "alias": "Hvidovre Kommune"
                },
                {
                    "value": 56230718,
                    "alias": "Friluftsr\u00e5det"
                },
                {
                    "value": 58271713,
                    "alias": "Ballerup Kommune"
                },
                {
                    "value": 60183112,
                    "alias": "Aller\u00f8d Kommune"
                },
                {
                    "value": 62547413,
                    "alias": "kl"
                },
                {
                    "value": 62761113,
                    "alias": "Gladsaxe Kommune"
                },
                {
                    "value": 63640719,
                    "alias": "Herlev Kommune"
                },
                {
                    "value": 64502018,
                    "alias": "Helsing\u00f8r Kommune"
                },
                {
                    "value": 64942212,
                    "alias": "K\u00f8benhavns Kommune"
                },
                {
                    "value": 65113015,
                    "alias": "Br\u00f8ndby Kommune"
                },
                {
                    "value": 65120119,
                    "alias": "Glostrup Kommune"
                },
                {
                    "value": 65307316,
                    "alias": "R\u00f8dovre Kommune"
                },
                {
                    "value": 66137112,
                    "alias": "Albertslund Kommune"
                },
                {
                    "value": 68534917,
                    "alias": "Solr\u00f8d Kommune"
                },
                {
                    "value": 69116418,
                    "alias": "Fredericia Kommune"
                },
                {
                    "value": 70960516,
                    "alias": "H\u00f8rsholm Kommune"
                },
                {
                    "value": 99999999,
                    "alias": "Nan"
                },
                {
                    "value": 100000113,
                    "alias": "Helsing\u00f8r Kommunes Beredskab"
                }
            ],
            "alias": "",
            "queryable": false,
            "sort_id": 80
        },
        "cvr_navn": {
            "type": "character varying",
            "comment": "Feltet benyttes til at overs\u00e6tte\/vise koden til tekst.",
            "num": 9,
            "full_type": "character varying(128)",
            "typname": "varchar",
            "is_array": false,
            "character_maximum_length": 128,
            "numeric_precision": null,
            "numeric_scale": null,
            "max_bytes": 512,
            "reference": null,
            "restriction": null,
            "alias": "",
            "queryable": true,
            "sort_id": 90
        },
        "kommunekode": {
            "type": "integer",
            "comment": "3-cifret kommunekode udfyldes via cvr_kode.",
            "num": 10,
            "full_type": "integer",
            "typname": "int4",
            "is_array": false,
            "character_maximum_length": null,
            "numeric_precision": 32,
            "numeric_scale": 0,
            "max_bytes": 4,
            "reference": null,
            "restriction": null,
            "alias": "",
            "queryable": false,
            "sort_id": 100
        },
        "bruger_id": {
            "type": "character varying",
            "comment": "Brugeridentifikation fra det f\u00e6lles offentlige brugerstyringssystem. Registreres automatisk ved oprettelse eller opdatering af objekter. Der er tale om brugeridentifikation af den medarbejder, der via det f\u00e6lles offentlige brugerstyringssystem har f\u00e5et tildelt rettigheder til at redigere i data.",
            "num": 11,
            "full_type": "character varying(128)",
            "typname": "varchar",
            "is_array": false,
            "character_maximum_length": 128,
            "numeric_precision": null,
            "numeric_scale": null,
            "max_bytes": 512,
            "reference": null,
            "restriction": null,
            "alias": "",
            "queryable": false,
            "sort_id": 110
        },
        "oprindkode": {
            "type": "integer",
            "comment": "Feltet benyttes til at angive en oprindelse via en kode.",
            "num": 12,
            "full_type": "integer",
            "typname": "int4",
            "is_array": false,
            "character_maximum_length": null,
            "numeric_precision": 32,
            "numeric_scale": 0,
            "max_bytes": 4,
            "reference": [
                "fkg.d_basis_oprindelse.oprindkode"
            ],
            "restriction": [
                {
                    "value": 0,
                    "alias": "Ikke udfyldt"
                },
                {
                    "value": 1,
                    "alias": "Ortofoto"
                },
                {
                    "value": 2,
                    "alias": "Matrikelkort"
                },
                {
                    "value": 3,
                    "alias": "Opm\u00e5ling"
                },
                {
                    "value": 4,
                    "alias": "FOT \/ Tekniske kort"
                },
                {
                    "value": 5,
                    "alias": "Modelberegning"
                },
                {
                    "value": 6,
                    "alias": "Tegning"
                },
                {
                    "value": 7,
                    "alias": "Felt-\/markbes\u00f8g"
                },
                {
                    "value": 8,
                    "alias": "Borgeranmeldelse"
                },
                {
                    "value": 9,
                    "alias": "Luftfoto (historiske 1944-1993)"
                },
                {
                    "value": 10,
                    "alias": "Skr\u00e5foto"
                },
                {
                    "value": 11,
                    "alias": "Andre foto"
                },
                {
                    "value": 12,
                    "alias": "3D"
                }
            ],
            "alias": "",
            "queryable": false,
            "sort_id": 120
        },
        "oprindelse": {
            "type": "character varying",
            "comment": "Feltet benyttes til at overs\u00e6tte\/vise koden til tekst.",
            "num": 13,
            "full_type": "character varying(35)",
            "typname": "varchar",
            "is_array": false,
            "character_maximum_length": 35,
            "numeric_precision": null,
            "numeric_scale": null,
            "max_bytes": 140,
            "reference": null,
            "restriction": null,
            "alias": "",
            "queryable": false,
            "sort_id": 130
        },
        "statuskode": {
            "type": "integer",
            "comment": "Feltet benyttes til at angive en status via en kode.",
            "num": 14,
            "full_type": "integer",
            "typname": "int4",
            "is_array": false,
            "character_maximum_length": null,
            "numeric_precision": 32,
            "numeric_scale": 0,
            "max_bytes": 4,
            "reference": [
                "fkg.d_basis_status.statuskode"
            ],
            "restriction": [
                {
                    "value": 0,
                    "alias": "Ukendt"
                },
                {
                    "value": 1,
                    "alias": "Kladde"
                },
                {
                    "value": 2,
                    "alias": "Forslag"
                },
                {
                    "value": 3,
                    "alias": "G\u00e6ldende \/ Vedtaget"
                },
                {
                    "value": 4,
                    "alias": "Ikke g\u00e6ldende \/ Aflyst"
                }
            ],
            "alias": "",
            "queryable": true,
            "sort_id": 140
        },
        "status": {
            "type": "character varying",
            "comment": "Feltet benyttes til at overs\u00e6tte\/vise koden til tekst.",
            "num": 15,
            "full_type": "character varying(30)",
            "typname": "varchar",
            "is_array": false,
            "character_maximum_length": 30,
            "numeric_precision": null,
            "numeric_scale": null,
            "max_bytes": 120,
            "reference": null,
            "restriction": null,
            "alias": "",
            "queryable": false,
            "sort_id": 150
        },
        "off_kode": {
            "type": "integer",
            "comment": "Feltet benyttes til at angive niveauet for tilg\u00e6ngelighed til objektet via en kode.",
            "num": 16,
            "full_type": "integer",
            "typname": "int4",
            "is_array": false,
            "character_maximum_length": null,
            "numeric_precision": 32,
            "numeric_scale": 0,
            "max_bytes": 4,
            "reference": [
                "fkg.d_basis_offentlig.off_kode"
            ],
            "restriction": [
                {
                    "value": 1,
                    "alias": "Synlig for alle"
                },
                {
                    "value": 2,
                    "alias": "Synlig for den ansvarlige myndighed"
                },
                {
                    "value": 3,
                    "alias": "Synlig for alle myndigheder, men ikke offentligheden"
                }
            ],
            "alias": "",
            "queryable": false,
            "sort_id": 160
        },
        "offentlig": {
            "type": "character varying",
            "comment": "Feltet benyttes til at angive niveauet for tilg\u00e6ngelighed til objektet.",
            "num": 17,
            "full_type": "character varying(60)",
            "typname": "varchar",
            "is_array": false,
            "character_maximum_length": 60,
            "numeric_precision": null,
            "numeric_scale": null,
            "max_bytes": 240,
            "reference": null,
            "restriction": null,
            "alias": "",
            "queryable": false,
            "sort_id": 170
        },
        "noegle": {
            "type": "character varying",
            "comment": "Fremmed n\u00f8gle til objektet i en anden databasetabel.",
            "num": 18,
            "full_type": "character varying(128)",
            "typname": "varchar",
            "is_array": false,
            "character_maximum_length": 128,
            "numeric_precision": null,
            "numeric_scale": null,
            "max_bytes": 512,
            "reference": null,
            "restriction": null,
            "alias": "",
            "queryable": false,
            "sort_id": 180
        },
        "note": {
            "type": "character varying",
            "comment": "Frit bem\u00e6rkningsfelt.",
            "num": 19,
            "full_type": "character varying(254)",
            "typname": "varchar",
            "is_array": false,
            "character_maximum_length": 254,
            "numeric_precision": null,
            "numeric_scale": null,
            "max_bytes": 1016,
            "reference": null,
            "restriction": null,
            "alias": "",
            "queryable": false,
            "sort_id": 190
        },
        "p_type_kode": {
            "type": "integer",
            "comment": "Kode for parkeringstyper. Eksempel: 4",
            "num": 20,
            "full_type": "integer",
            "typname": "int4",
            "is_array": false,
            "character_maximum_length": null,
            "numeric_precision": 32,
            "numeric_scale": 0,
            "max_bytes": 4,
            "reference": [
                "fkg.d_5602_p_type.p_type_kode"
            ],
            "restriction": [
                {
                    "value": 1,
                    "alias": "Betalingszone"
                },
                {
                    "value": 2,
                    "alias": "Betalingsfri zone"
                },
                {
                    "value": 3,
                    "alias": "Beboerparkering"
                },
                {
                    "value": 4,
                    "alias": "Erhvervsparkering"
                },
                {
                    "value": 5,
                    "alias": "P-licens"
                },
                {
                    "value": 98,
                    "alias": "Andet"
                },
                {
                    "value": 99,
                    "alias": "Ukendt"
                }
            ],
            "alias": "",
            "queryable": false,
            "sort_id": 200
        },
        "p_type": {
            "type": "character varying",
            "comment": "Parkeringstyper. Eksempel: Erhvervsparkering",
            "num": 21,
            "full_type": "character varying(20)",
            "typname": "varchar",
            "is_array": false,
            "character_maximum_length": 20,
            "numeric_precision": null,
            "numeric_scale": null,
            "max_bytes": 80,
            "reference": null,
            "restriction": null,
            "alias": "",
            "queryable": true,
            "sort_id": 202
        },
        "p_zone_nr": {
            "type": "character varying",
            "comment": "Angiv nummer for zonen - entydigt indenfor. Eksempel: 0165-456",
            "num": 22,
            "full_type": "character varying(50)",
            "typname": "varchar",
            "is_array": false,
            "character_maximum_length": 50,
            "numeric_precision": null,
            "numeric_scale": null,
            "max_bytes": 200,
            "reference": null,
            "restriction": null,
            "alias": "",
            "queryable": false,
            "sort_id": 204
        },
        "omraade": {
            "type": "character varying",
            "comment": "Unikt omr\u00e5denavn",
            "num": 23,
            "full_type": "character varying(128)",
            "typname": "varchar",
            "is_array": false,
            "character_maximum_length": 128,
            "numeric_precision": null,
            "numeric_scale": null,
            "max_bytes": 512,
            "reference": null,
            "restriction": null,
            "alias": "",
            "queryable": false,
            "sort_id": 206
        },
        "koordinat_east": {
            "type": "character varying",
            "comment": "Koordinat til brug i navigations systemer.",
            "num": 56,
            "full_type": "character varying(128)",
            "typname": "varchar",
            "is_array": false,
            "character_maximum_length": 128,
            "numeric_precision": null,
            "numeric_scale": null,
            "max_bytes": 512,
            "reference": null,
            "restriction": null,
            "alias": "",
            "queryable": false,
            "sort_id": 207
        },
        "koordinat_north": {
            "type": "character varying",
            "comment": "Koordinat til brug i navigations systemer.",
            "num": 57,
            "full_type": "character varying(128)",
            "typname": "varchar",
            "is_array": false,
            "character_maximum_length": 128,
            "numeric_precision": null,
            "numeric_scale": null,
            "max_bytes": 512,
            "reference": null,
            "restriction": null,
            "alias": "",
            "queryable": false,
            "sort_id": 208
        },
        "p_tid_kode": {
            "type": "integer",
            "comment": "Kode for max parkeringstid. Eksempel: 3",
            "num": 24,
            "full_type": "integer",
            "typname": "int4",
            "is_array": false,
            "character_maximum_length": null,
            "numeric_precision": 32,
            "numeric_scale": 0,
            "max_bytes": 4,
            "reference": [
                "fkg.d_5602_p_tid.p_tid_kode"
            ],
            "restriction": [
                {
                    "value": 1,
                    "alias": "Max 1 time"
                },
                {
                    "value": 2,
                    "alias": "Max 2 timer"
                },
                {
                    "value": 3,
                    "alias": "Max 3 timer"
                },
                {
                    "value": 4,
                    "alias": "Max 4 timer"
                },
                {
                    "value": 5,
                    "alias": "Max 5 timer"
                },
                {
                    "value": 6,
                    "alias": "Max 6 timer"
                },
                {
                    "value": 7,
                    "alias": "Max 7 timer"
                },
                {
                    "value": 8,
                    "alias": "Max 8 timer"
                },
                {
                    "value": 9,
                    "alias": "Max 9 timer"
                },
                {
                    "value": 10,
                    "alias": "Max 10 timer"
                },
                {
                    "value": 11,
                    "alias": "Max 11 timer"
                },
                {
                    "value": 12,
                    "alias": "Max 12 timer"
                },
                {
                    "value": 13,
                    "alias": "Max 24 timer"
                },
                {
                    "value": 14,
                    "alias": "Max 48 timer"
                },
                {
                    "value": 15,
                    "alias": "Max 15 minutter"
                },
                {
                    "value": 30,
                    "alias": "Max 30 minutter"
                },
                {
                    "value": 45,
                    "alias": "Max 45 minutter"
                },
                {
                    "value": 97,
                    "alias": "Uden begr\u00e6nsning"
                },
                {
                    "value": 98,
                    "alias": "Andet"
                },
                {
                    "value": 99,
                    "alias": "Ukendt"
                }
            ],
            "alias": "",
            "queryable": false,
            "sort_id": 209
        },
        "p_tid": {
            "type": "character varying",
            "comment": "Max tid i minutter\/timer for parkering. Eksempel: max 3 timer",
            "num": 25,
            "full_type": "character varying(30)",
            "typname": "varchar",
            "is_array": false,
            "character_maximum_length": 30,
            "numeric_precision": null,
            "numeric_scale": null,
            "max_bytes": 120,
            "reference": null,
            "restriction": null,
            "alias": "",
            "queryable": true,
            "sort_id": 210
        },
        "p_hverdag_start": {
            "type": "time without time zone",
            "comment": "Starttidspunkt for periode med parkeringsforbud p\u00e5 hverdage. B\u00f8r sammen med sluttidspunkt svare til skiltning. Eksempel: 7:00",
            "num": 26,
            "full_type": "time without time zone",
            "typname": "time",
            "is_array": false,
            "character_maximum_length": null,
            "numeric_precision": null,
            "numeric_scale": null,
            "max_bytes": 8,
            "reference": null,
            "restriction": null,
            "alias": "",
            "queryable": false,
            "sort_id": 212
        },
        "p_hverdag_slut": {
            "type": "time without time zone",
            "comment": "Sluttidspunkt for periode med parkeringsforbud p\u00e5 hverdage B\u00f8r sammen med starttidspunkt svare til skiltning. Eksempel: 17:00",
            "num": 27,
            "full_type": "time without time zone",
            "typname": "time",
            "is_array": false,
            "character_maximum_length": null,
            "numeric_precision": null,
            "numeric_scale": null,
            "max_bytes": 8,
            "reference": null,
            "restriction": null,
            "alias": "",
            "queryable": false,
            "sort_id": 214
        },
        "p_loerdag_start": {
            "type": "time without time zone",
            "comment": "Starttidspunkt for periode med parkeringsforbud p\u00e5 l\u00f8rdage. B\u00f8r sammen med sluttidspunkt svare til skiltning (dog uden parenteser). Eksempel: 8:00",
            "num": 28,
            "full_type": "time without time zone",
            "typname": "time",
            "is_array": false,
            "character_maximum_length": null,
            "numeric_precision": null,
            "numeric_scale": null,
            "max_bytes": 8,
            "reference": null,
            "restriction": null,
            "alias": "",
            "queryable": false,
            "sort_id": 216
        },
        "p_loerdag_slut": {
            "type": "time without time zone",
            "comment": "Sluttidspunkt for periode med parkeringsforbud p\u00e5 l\u00f8rdage. B\u00f8r sammen med starttidspunkt svare til skiltning (dog uden parenteser). Eksempel: 14:00",
            "num": 29,
            "full_type": "time without time zone",
            "typname": "time",
            "is_array": false,
            "character_maximum_length": null,
            "numeric_precision": null,
            "numeric_scale": null,
            "max_bytes": 8,
            "reference": null,
            "restriction": null,
            "alias": "",
            "queryable": false,
            "sort_id": 218
        },
        "p_soendag_start": {
            "type": "time without time zone",
            "comment": "Starttidspunkt for periode med parkeringsforbud s\u00f8n- og helligdag. B\u00f8r sammen med sluttidspunkt svare til skiltning (dog uden parenteser) Hvis ingen begr\u00e6nsning s\u00f8ndage \u2013 undlad udfyldelse. Eksempel: 8:00",
            "num": 30,
            "full_type": "time without time zone",
            "typname": "time",
            "is_array": false,
            "character_maximum_length": null,
            "numeric_precision": null,
            "numeric_scale": null,
            "max_bytes": 8,
            "reference": null,
            "restriction": null,
            "alias": "",
            "queryable": false,
            "sort_id": 220
        },
        "p_soendag_slut": {
            "type": "time without time zone",
            "comment": "Sluttidspunkt for periode med parkeringsforbud s\u00f8n- og helligdag. B\u00f8r sammen med starttidspunkt svare til skiltning (dog uden parenteser) Hvis ingen begr\u00e6nsning s\u00f8ndage \u2013 undlad udfyldelse. Eksempel: 14:00",
            "num": 31,
            "full_type": "time without time zone",
            "typname": "time",
            "is_array": false,
            "character_maximum_length": null,
            "numeric_precision": null,
            "numeric_scale": null,
            "max_bytes": 8,
            "reference": null,
            "restriction": null,
            "alias": "",
            "queryable": false,
            "sort_id": 222
        },
        "p_pris_time": {
            "type": "double precision",
            "comment": "kr\/timen for omr\u00e5de med betalingsparkering. Eksempel: 7,50",
            "num": 32,
            "full_type": "double precision",
            "typname": "float8",
            "is_array": false,
            "character_maximum_length": null,
            "numeric_precision": 53,
            "numeric_scale": null,
            "max_bytes": 8,
            "reference": null,
            "restriction": null,
            "alias": "",
            "queryable": false,
            "sort_id": 224
        },
        "p_pris_fri_startperiode": {
            "type": "integer",
            "comment": "Hvor l\u00e6nge m\u00e5 man holde gratis p\u00e5 en betalingsplads? Angiv i minutter. Eksempel: 30",
            "num": 33,
            "full_type": "integer",
            "typname": "int4",
            "is_array": false,
            "character_maximum_length": null,
            "numeric_precision": 32,
            "numeric_scale": 0,
            "max_bytes": 4,
            "reference": null,
            "restriction": null,
            "alias": "",
            "queryable": false,
            "sort_id": 226
        },
        "p_start_betalingsperiode_hverdag": {
            "type": "time without time zone",
            "comment": "Starttidspunkt for periode, hvor der skal betales for parkering - hverdage. Eksempel: 7:00",
            "num": 34,
            "full_type": "time without time zone",
            "typname": "time",
            "is_array": false,
            "character_maximum_length": null,
            "numeric_precision": null,
            "numeric_scale": null,
            "max_bytes": 8,
            "reference": null,
            "restriction": null,
            "alias": "",
            "queryable": false,
            "sort_id": 228
        },
        "p_slut_betalingsperiode_hverdag": {
            "type": "time without time zone",
            "comment": "Sluttidspunkt for periode, hvor der skal betales for parkering - hverdage. Eksemepel: 22:00",
            "num": 35,
            "full_type": "time without time zone",
            "typname": "time",
            "is_array": false,
            "character_maximum_length": null,
            "numeric_precision": null,
            "numeric_scale": null,
            "max_bytes": 8,
            "reference": null,
            "restriction": null,
            "alias": "",
            "queryable": false,
            "sort_id": 230
        },
        "p_start_betalingsperiode_loerdag": {
            "type": "time without time zone",
            "comment": "Starttidspunkt for periode, hvor der skal betales for parkering \u2013 l\u00f8rdage. Eksempel: 16:00",
            "num": 36,
            "full_type": "time without time zone",
            "typname": "time",
            "is_array": false,
            "character_maximum_length": null,
            "numeric_precision": null,
            "numeric_scale": null,
            "max_bytes": 8,
            "reference": null,
            "restriction": null,
            "alias": "",
            "queryable": false,
            "sort_id": 232
        },
        "p_slut_betalingsperiode_loerdag": {
            "type": "time without time zone",
            "comment": "Sluttidspunkt for periode, hvor der skal betales for parkering \u2013 l\u00f8rdage. Eksempel: 22:00",
            "num": 37,
            "full_type": "time without time zone",
            "typname": "time",
            "is_array": false,
            "character_maximum_length": null,
            "numeric_precision": null,
            "numeric_scale": null,
            "max_bytes": 8,
            "reference": null,
            "restriction": null,
            "alias": "",
            "queryable": false,
            "sort_id": 234
        },
        "p_start_betalingsperiode_soendag": {
            "type": "time without time zone",
            "comment": "Starttidspunkt for periode, hvor der skal betales for parkering \u2013 s\u00f8n- og helligdage. Eksempel: 16:00",
            "num": 38,
            "full_type": "time without time zone",
            "typname": "time",
            "is_array": false,
            "character_maximum_length": null,
            "numeric_precision": null,
            "numeric_scale": null,
            "max_bytes": 8,
            "reference": null,
            "restriction": null,
            "alias": "",
            "queryable": false,
            "sort_id": 236
        },
        "p_slut_betalingsperiode_soendag": {
            "type": "time without time zone",
            "comment": "Sluttidspunkt for periode, hvor der skal betales for parkering \u2013 s\u00f8n- og helligdage. Eksempel: 22:00",
            "num": 39,
            "full_type": "time without time zone",
            "typname": "time",
            "is_array": false,
            "character_maximum_length": null,
            "numeric_precision": null,
            "numeric_scale": null,
            "max_bytes": 8,
            "reference": null,
            "restriction": null,
            "alias": "",
            "queryable": false,
            "sort_id": 238
        },
        "p_pladser_personbil": {
            "type": "integer",
            "comment": "Antal p-pladser i P-zonen til personbiler parkering. Eksempel: 57",
            "num": 40,
            "full_type": "integer",
            "typname": "int4",
            "is_array": false,
            "character_maximum_length": null,
            "numeric_precision": 32,
            "numeric_scale": 0,
            "max_bytes": 4,
            "reference": null,
            "restriction": null,
            "alias": "",
            "queryable": false,
            "sort_id": 240
        },
        "p_pladser_handicap": {
            "type": "integer",
            "comment": "Antal p-pladser i P-zonen til handicap parkering. Eksempel: 10",
            "num": 41,
            "full_type": "integer",
            "typname": "int4",
            "is_array": false,
            "character_maximum_length": null,
            "numeric_precision": 32,
            "numeric_scale": 0,
            "max_bytes": 4,
            "reference": null,
            "restriction": null,
            "alias": "",
            "queryable": false,
            "sort_id": 242
        },
        "p_pladser_elbil": {
            "type": "integer",
            "comment": "Antal p-pladser i P-zonen til elbiler. Eksempel: 6",
            "num": 42,
            "full_type": "integer",
            "typname": "int4",
            "is_array": false,
            "character_maximum_length": null,
            "numeric_precision": 32,
            "numeric_scale": 0,
            "max_bytes": 4,
            "reference": null,
            "restriction": null,
            "alias": "",
            "queryable": false,
            "sort_id": 244
        },
        "p_pladser_delebil": {
            "type": "integer",
            "comment": "Antal p-pladser i P-zonen reserveret til delebiler. Eksempel: 3",
            "num": 43,
            "full_type": "integer",
            "typname": "int4",
            "is_array": false,
            "character_maximum_length": null,
            "numeric_precision": 32,
            "numeric_scale": 0,
            "max_bytes": 4,
            "reference": null,
            "restriction": null,
            "alias": "",
            "queryable": false,
            "sort_id": 246
        },
        "p_pladser_lastbil": {
            "type": "integer",
            "comment": "Antal p-pladser i P-zonen til lastbiler parkering p\u00e5 parkeringsomr\u00e5det. Eksempel: 0",
            "num": 44,
            "full_type": "integer",
            "typname": "int4",
            "is_array": false,
            "character_maximum_length": null,
            "numeric_precision": 32,
            "numeric_scale": 0,
            "max_bytes": 4,
            "reference": null,
            "restriction": null,
            "alias": "",
            "queryable": false,
            "sort_id": 248
        },
        "p_pladser_mc": {
            "type": "integer",
            "comment": "Antal p-pladser i P-zonen til motorcykler. Eksempel: 57",
            "num": 45,
            "full_type": "integer",
            "typname": "int4",
            "is_array": false,
            "character_maximum_length": null,
            "numeric_precision": 32,
            "numeric_scale": 0,
            "max_bytes": 4,
            "reference": null,
            "restriction": null,
            "alias": "",
            "queryable": false,
            "sort_id": 250
        },
        "p_pladser_erhverv": {
            "type": "integer",
            "comment": "Antal p-pladser i p-zonen til erhvervsparkering. Eksempel: 4",
            "num": 46,
            "full_type": "integer",
            "typname": "int4",
            "is_array": false,
            "character_maximum_length": null,
            "numeric_precision": 32,
            "numeric_scale": 0,
            "max_bytes": 4,
            "reference": null,
            "restriction": null,
            "alias": "",
            "queryable": false,
            "sort_id": 252
        },
        "p_plads_taxaholdeplads": {
            "type": "integer",
            "comment": "Antal p-pladser i p-zonen reserveret til taxa-holdepladser. Eksempel: 3",
            "num": 47,
            "full_type": "integer",
            "typname": "int4",
            "is_array": false,
            "character_maximum_length": null,
            "numeric_precision": 32,
            "numeric_scale": 0,
            "max_bytes": 4,
            "reference": null,
            "restriction": null,
            "alias": "",
            "queryable": false,
            "sort_id": 254
        },
        "p_pladser_cykel": {
            "type": "integer",
            "comment": "Antal pladser i P-zonen til cykelparkering. Eksempel: 57",
            "num": 48,
            "full_type": "integer",
            "typname": "int4",
            "is_array": false,
            "character_maximum_length": null,
            "numeric_precision": 32,
            "numeric_scale": 0,
            "max_bytes": 4,
            "reference": null,
            "restriction": null,
            "alias": "",
            "queryable": false,
            "sort_id": 256
        },
        "p_pladser_ladcykel": {
            "type": "integer",
            "comment": "Antal pladser i P-zonen til parkering af ladcykler. Eksempel: 100",
            "num": 49,
            "full_type": "integer",
            "typname": "int4",
            "is_array": false,
            "character_maximum_length": null,
            "numeric_precision": 32,
            "numeric_scale": 0,
            "max_bytes": 4,
            "reference": null,
            "restriction": null,
            "alias": "",
            "queryable": false,
            "sort_id": 258
        },
        "p_pladser_cykel_aflaast": {
            "type": "integer",
            "comment": "Antal pladser til cykler i aflukket\/afl\u00e5st cykelskur. Eksempel: 100",
            "num": 50,
            "full_type": "integer",
            "typname": "int4",
            "is_array": false,
            "character_maximum_length": null,
            "numeric_precision": 32,
            "numeric_scale": 0,
            "max_bytes": 4,
            "reference": null,
            "restriction": null,
            "alias": "",
            "queryable": false,
            "sort_id": 260
        },
        "p_pladser_cykel_overdaekket": {
            "type": "integer",
            "comment": "Antal pladser til cykler i overd\u00e6kket cykelskur. Eksempel: 100",
            "num": 51,
            "full_type": "integer",
            "typname": "int4",
            "is_array": false,
            "character_maximum_length": null,
            "numeric_precision": 32,
            "numeric_scale": 0,
            "max_bytes": 4,
            "reference": null,
            "restriction": null,
            "alias": "",
            "queryable": false,
            "sort_id": 262
        },
        "link": {
            "type": "character varying",
            "comment": "URL-link",
            "num": 52,
            "full_type": "character varying(1024)",
            "typname": "varchar",
            "is_array": false,
            "character_maximum_length": 1024,
            "numeric_precision": null,
            "numeric_scale": null,
            "max_bytes": 4096,
            "reference": null,
            "restriction": null,
            "alias": "",
            "queryable": false,
            "sort_id": 460
        },
        "link1": {
            "type": "character varying",
            "comment": "URL-link",
            "num": 53,
            "full_type": "character varying(1024)",
            "typname": "varchar",
            "is_array": false,
            "character_maximum_length": 1024,
            "numeric_precision": null,
            "numeric_scale": null,
            "max_bytes": 4096,
            "reference": null,
            "restriction": null,
            "alias": "",
            "queryable": false,
            "sort_id": 470
        },
        "adr_id": {
            "type": "uuid",
            "comment": "Entydig databasen\u00f8gle fra det officielle adresseregister (UUID).",
            "num": 55,
            "full_type": "uuid",
            "typname": "uuid",
            "is_array": false,
            "character_maximum_length": null,
            "numeric_precision": null,
            "numeric_scale": null,
            "max_bytes": 16,
            "reference": null,
            "restriction": null,
            "alias": "",
            "queryable": false,
            "sort_id": 500
        },
        "vejkode": {
            "type": "integer",
            "comment": "Vejkode (DAR)",
            "num": 58,
            "full_type": "integer",
            "typname": "int4",
            "is_array": false,
            "character_maximum_length": null,
            "numeric_precision": 32,
            "numeric_scale": 0,
            "max_bytes": 4,
            "reference": null,
            "restriction": null,
            "alias": "",
            "queryable": false,
            "sort_id": 502
        },
        "husnr": {
            "type": "character varying",
            "comment": "Husnummer",
            "num": 60,
            "full_type": "character varying(4)",
            "typname": "varchar",
            "is_array": false,
            "character_maximum_length": 4,
            "numeric_precision": null,
            "numeric_scale": null,
            "max_bytes": 16,
            "reference": null,
            "restriction": null,
            "alias": "",
            "queryable": false,
            "sort_id": 504
        },
        "vejnavn": {
            "type": "character varying",
            "comment": "Vejnavn der refererer til vejkode",
            "num": 59,
            "full_type": "character varying(40)",
            "typname": "varchar",
            "is_array": false,
            "character_maximum_length": 40,
            "numeric_precision": null,
            "numeric_scale": null,
            "max_bytes": 160,
            "reference": null,
            "restriction": null,
            "alias": "",
            "queryable": false,
            "sort_id": 507
        },
        "postnr": {
            "type": "integer",
            "comment": "Postnr",
            "num": 61,
            "full_type": "integer",
            "typname": "int4",
            "is_array": false,
            "character_maximum_length": null,
            "numeric_precision": 32,
            "numeric_scale": 0,
            "max_bytes": 4,
            "reference": null,
            "restriction": null,
            "alias": "",
            "queryable": false,
            "sort_id": 508
        },
        "postnr_by": {
            "type": "character varying",
            "comment": "By der refererer til Postnr",
            "num": 62,
            "full_type": "character varying(128)",
            "typname": "varchar",
            "is_array": false,
            "character_maximum_length": 128,
            "numeric_precision": null,
            "numeric_scale": null,
            "max_bytes": 512,
            "reference": null,
            "restriction": null,
            "alias": "",
            "queryable": false,
            "sort_id": 509
        },
        "geometri": {
            "type": "geometry",
            "comment": "Geometrisk registrering af objekt \u2013 styres af database. Koordinatpr\u00e6cision defineret til 0,001 (millimeter). Et tema kan kun indeholde en geometritype (flade\/linje\/punkt).  Der er mulighed for multigeometrier.",
            "num": 54,
            "full_type": "geometry(MultiPolygon,25832)",
            "typname": "geometry",
            "is_array": false,
            "character_maximum_length": null,
            "numeric_precision": null,
            "numeric_scale": null,
            "max_bytes": null,
            "reference": null,
            "restriction": null,
            "geom_type": "MultiPolygon",
            "srid": "25832",
            "alias": "",
            "queryable": false,
            "sort_id": 999
        }
    },
    "children": null,
    "meta": {
        "tiled": false,
        "formaal": "Oplyse sagsbehandler og borger via selvbetjeningsl\u00f8sninger, hvordan parkeringsforholdene er begr\u00e6nset i zonen.",
        "temakode": "5602",
        "temanavn": "P-zoner",
        "kle_koder": "05.09.02, 05.09.06, 05.09.08",
        "meta_desc": "<p>\nP-zoner anvendes som udgangspunkt som en st\u00f8rre fladeregistrering for en samling af et antal parkeringspladser, hvor der g\u00e6lder\nsamme regler for, hvorn\u00e5r man m\u00e5 parkere og hvorn\u00e5r der skal betales for parkering. Der tages udgangspunkt i parkeringsregler for \nperson- og varebiler. For eksempel en parkeringsplads ved et r\u00e5dhus, hvor der g\u00e6lder samme regler. Der kan til fladen registreres \nb\u00e5de, hvor mange pladser, der findes til diverse typer af k\u00f8ret\u00f8jer samt regler for parkering. Der er ogs\u00e5 gjort plads til registrering af \ncykelparkering m.m. i omr\u00e5det \u2013 selv om k\u00f8ret\u00f8jet ikke er underlagt begr\u00e6nsninger i tid eller betalingskrav.\nP-zoner kan alternativt ogs\u00e5 bruges p\u00e5 \u201denkeltniveau\u201d, hvor man har brug for at f\u00e5 hver parkeringsb\u00e5s til at fremst\u00e5 som en flade. Det \nanbefales dog at bruge 5.7.4 til dette, idet dette tema giver mulighed for at s\u00e6tte en punktregistrering for hver enkelt parkeringsb\u00e5s. \nP\u00e5 denne m\u00e5de supplerer de to temalag hinanden: P-zoner er den overordnet samlede flade, der angiver omfanget af \nparkeringspladsen og p-pladser kan vise de enkelte parkeringsb\u00e5se indenfor p-zonen.\n<\/p>\n<p>\n  Vil du vide mere? P\u00e5 \n  <a href=\"https:\/\/confluence.sdfi.dk\/pages\/viewpage.action?pageId=191398876\" target=\"_blank\">\n    confluence \n  <\/a> \n  finder du GeoFA\u2019s vejledningsunivers \u2013 tag et kig.\n<\/p>",
        "definition": "P-zoner anvendes som udgangspunkt som en st\u00f8rre fladeregistrering for en samling af et antal parkeringspladser, hvor der g\u00e6lder\nsamme regler for, hvorn\u00e5r man m\u00e5 parkere og hvorn\u00e5r der skal betales for parkering. Der tages udgangspunkt i parkeringsregler for\nperson- og varebiler. For eksempel en parkeringsplads ved et r\u00e5dhus, hvor der g\u00e6lder samme regler. Der kan til fladen registreres\nb\u00e5de, hvor mange pladser, der findes til diverse typer af k\u00f8ret\u00f8jer samt regler for parkering. Der er ogs\u00e5 gjort plads til registrering af\ncykelparkering m.m. i omr\u00e5det \u2013 selv om k\u00f8ret\u00f8jet ikke er underlagt begr\u00e6nsninger i tid eller betalingskrav.\nP-zoner kan alternativt ogs\u00e5 bruges p\u00e5 \u201denkeltniveau\u201d, hvor man har brug for at f\u00e5 hver parkeringsb\u00e5s til at fremst\u00e5 som en flade. Det\nanbefales dog at bruge 5.7.4 til dette, idet dette tema giver mulighed for at s\u00e6tte en punktregistrering for hver enkelt parkeringsb\u00e5s.\nP\u00e5 denne m\u00e5de supplerer de to temalag hinanden: P-zoner er den overordnet samlede flade, der angiver omfanget af\nparkeringspladsen og p-pladser kan vise de enkelte parkeringsb\u00e5se indenfor p-zonen.",
        "noegle_ord": "Parkering, P-plads, parkeringszoner",
        "beskrivelse": "",
        "lovgrundlag": "",
        "single_tile": false,
        "geometritype": "Flade",
        "hover_active": false,
        "max_features": "500",
        "sql_conflict": "",
        "vector_style": "",
        "default_match": "any",
        "filter_config": "",
        "info_function": "",
        "info_template": "",
        "load_strategy": "s",
        "referenced_by": "",
        "cache_utf_grid": false,
        "point_to_layer": "",
        "use_clustering": false,
        "vidi_sub_group": "",
        "buffer_conflict": "",
        "filter_required": false,
        "reload_callback": "",
        "reload_interval": "",
        "select_function": "",
        "vector_max_zoom": "",
        "vector_min_zoom": "",
        "vidi_layer_type": "t,v",
        "filter_immutable": false,
        "tooltip_template": "",
        "accordion_summery": "",
        "disable_check_box": false,
        "entydige_objekter": "",
        "tiles_service_uri": "",
        "default_layer_type": "t",
        "default_open_tools": "[\"filters\"]",
        "predefined_filters": "",
        "show_table_on_side": false,
        "info_template_hover": "",
        "minimum_stoerrelser": "",
        "sql_conflict_header": "",
        "vidi_layer_editable": true,
        "zoom_on_table_click": false,
        "filter_html_template": "",
        "line_highlight_style": "",
        "tiles_selected_style": "",
        "geometrisk_konsistens": "Ingen overlap.",
        "info_element_selector": "",
        "noegleord_hovedgruppe": "Transportnet",
        "registreringsinstruks": "Fladen tegnes med snap til GeoDanmark-vejmidte ud for skilte med P-zonen. Dette skilt vil ofte kunne\ngenkendes p\u00e5 ortofoto. Ellers benyttes skr\u00e5foto eller street-view.",
        "klassificering_opdeling": "",
        "long_conflict_meta_desc": "",
        "accordion_summery_prefix": "",
        "short_conflict_meta_desc": "",
        "max_zoom_level_table_click": "17",
        "disable_vector_feature_info": false,
        "geometrisk_konsistens_andre": ""
    }
}